amsdal_langgraph/Third-Party Materials - AMSDAL Dependencies - License Notices.md
amsdal_langgraph/__about__.py
amsdal_langgraph/__init__.py
amsdal_langgraph/app.py
amsdal_langgraph/checkpoint.py
amsdal_langgraph/py.typed
amsdal_langgraph/utils.py
amsdal_langgraph/migrations/0000_initial.py
amsdal_langgraph/models/__init__.py
amsdal_langgraph/models/checkpoint.py
amsdal_langgraph/models/checkpoint_writes.py
amsdal_langgraph-0.1.1.dist-info/METADATA
amsdal_langgraph-0.1.1.dist-info/WHEEL
amsdal_langgraph-0.1.1.dist-info/RECORD
